setup.cfg
setup.py
clisheet.egg-info/PKG-INFO
clisheet.egg-info/SOURCES.txt
clisheet.egg-info/dependency_links.txt
clisheet.egg-info/entry_points.txt
clisheet.egg-info/not-zip-safe
clisheet.egg-info/pbr.json
clisheet.egg-info/requires.txt
clisheet.egg-info/top_level.txt
timesheet/__init__.py
timesheet/mail.py
timesheet/main.py
timesheet/models.py
timesheet/utils.py