Metadata-Version: 1.1
Name: clisheet
Version: 0.0.4
Summary: A command line tool for time tracking
Home-page: https://github.com/shangsunset/clisheet
Author: Yeshen Shang
Author-email: shangsunset@gmail.com
License: UNKNOWN
Download-URL: https://github.com/shangsunset/clisheet/tarball/0.1
Keywords: time tracking cli
Platform: UNKNOWN
